{"media_id": "77488321", "local_id": "NS112\n", "title": "File:Victoria_Strandin,_dancer_-_SMV_-_NS112.tif", "thumbnail": "https://upload.wikimedia.org/wikipedia/commons/thumb/0/0f/Victoria_Strandin,_dancer_-_SMV_-_NS112.tif/500px-Victoria_Strandin,_dancer_-_SMV_-_NS112.tif.jpg", "desc": " Victoria Strandin, dansare, i ok\u00e4nd f\u00f6rest\u00e4llning ca 1910. Skannat glasnegativ\n", "auto_desc": {"translatedText": "Victoria Strandin, dancer, in unknown performance about 1910. Scanned glass negative", "input": " Victoria Strandin, dansare, i ok\u00e4nd f\u00f6rest\u00e4llning ca 1910. Skannat glasnegativ\n"}}