{"media_id": "77465275", "local_id": "NL045\n", "title": "File:M\u00e4rtha_Lindl\u00f6f,_actor_-_SMV_-_NL045.tif", "thumbnail": "https://upload.wikimedia.org/wikipedia/commons/thumb/0/0d/M\u00e4rtha_Lindl\u00f6f,_actor_-_SMV_-_NL045.tif/500px-M\u00e4rtha_Lindl\u00f6f,_actor_-_SMV_-_NL045.tif.jpg", "desc": " M\u00e4rtha Lindl\u00f6f, sk\u00e5despelare. Odaterat portr\u00e4tt ca 1906. Skannat glasnegativ\n", "auto_desc": {"translatedText": "M\u00e4rtha Lindl\u00f6f, actor. Undated portrait about 1906. Scanned glass negative", "input": " M\u00e4rtha Lindl\u00f6f, sk\u00e5despelare. Odaterat portr\u00e4tt ca 1906. Skannat glasnegativ\n"}}