{"media_id": "77483994", "local_id": "NR024\n", "title": "File:Constance_Gibson_and_Lisa_Ranft,_actors_-_SMV_-_NR024.tif", "thumbnail": "https://upload.wikimedia.org/wikipedia/commons/thumb/6/69/Constance_Gibson_and_Lisa_Ranft,_actors_-_SMV_-_NR024.tif/500px-Constance_Gibson_and_Lisa_Ranft,_actors_-_SMV_-_NR024.tif.jpg", "desc": " Constance Gibson och Lisa Ranft, sk\u00e5despelare och systrar. Odaterat foto ca 1907. Skannat glasnegativ\n", "auto_desc": {"translatedText": "Constance Gibson and Lisa Ranft, actors and sisters. Undated photo about 1907. Scanned glass negative", "input": " Constance Gibson och Lisa Ranft, sk\u00e5despelare och systrar. Odaterat foto ca 1907. Skannat glasnegativ\n"}}