{"media_id": "77442357", "local_id": "NB088\n", "title": "File:Harriet_Bosse,_actor_-_SMV_-_NB088.tif", "thumbnail": "https://upload.wikimedia.org/wikipedia/commons/thumb/0/0d/Harriet_Bosse,_actor_-_SMV_-_NB088.tif/500px-Harriet_Bosse,_actor_-_SMV_-_NB088.tif.jpg", "desc": " Harriet Bosse, sk\u00e5despelare. Odaterat portr\u00e4tt ca 1910. Skannat glasnegativ\n", "auto_desc": {"translatedText": "Harriet Bosse, actor. Undated portrait about 1910. Scanned glass negative", "input": " Harriet Bosse, sk\u00e5despelare. Odaterat portr\u00e4tt ca 1910. Skannat glasnegativ\n"}}