{"media_id": "77490177", "local_id": "NT033\n", "title": "File:Vera_Tichani,_dancer_-_SMV_-_NT033.tif", "thumbnail": "https://upload.wikimedia.org/wikipedia/commons/thumb/e/e9/Vera_Tichani,_dancer_-_SMV_-_NT033.tif/500px-Vera_Tichani,_dancer_-_SMV_-_NT033.tif.jpg", "desc": " Vera Tichani, dansare, i ok\u00e4nd f\u00f6rest\u00e4llning ca 1910. Skannat glasnegativ\n", "auto_desc": {"translatedText": "Vera Tichani, dancer, in unknown performance about 1910. Scanned glass negative", "input": " Vera Tichani, dansare, i ok\u00e4nd f\u00f6rest\u00e4llning ca 1910. Skannat glasnegativ\n"}}