{"media_id": "77441117", "local_id": "NB061\n", "title": "File:Evelyne_Bergstr\u00f6m,_dancer_-_SMV_-_NB061.tif", "thumbnail": "https://upload.wikimedia.org/wikipedia/commons/thumb/8/89/Evelyne_Bergstr\u00f6m,_dancer_-_SMV_-_NB061.tif/500px-Evelyne_Bergstr\u00f6m,_dancer_-_SMV_-_NB061.tif.jpg", "desc": " Evelyne Bergstr\u00f6m, dansare, i ok\u00e4nd f\u00f6rest\u00e4llning ca 1905. Skannat glasnegativ\n", "auto_desc": {"translatedText": "Evelyne Bergstr\u00f6m, dancer, in unknown performance about 1905. Scanned glass negative", "input": " Evelyne Bergstr\u00f6m, dansare, i ok\u00e4nd f\u00f6rest\u00e4llning ca 1905. Skannat glasnegativ\n"}}