{"media_id": "77462697", "local_id": "NJ022\n", "title": "File:Matilda_Jungstedt,_opera_singer_-_SMV_-_NJ022.tif", "thumbnail": "https://upload.wikimedia.org/wikipedia/commons/thumb/9/9c/Matilda_Jungstedt,_opera_singer_-_SMV_-_NJ022.tif/500px-Matilda_Jungstedt,_opera_singer_-_SMV_-_NJ022.tif.jpg", "desc": " Matilda Jungstedt, operas\u00e5ngare. Odaterat portr\u00e4tt ca 1913. Skannat glasnegativ\n", "auto_desc": {"translatedText": "Matilda Jungstedt, opera singer. Undated portrait about 1913. Scanned glass negative", "input": " Matilda Jungstedt, operas\u00e5ngare. Odaterat portr\u00e4tt ca 1913. Skannat glasnegativ\n"}}