{"media_id": "77483535", "local_id": "NR010\n", "title": "File:Lisa_and_Albert_Ranft,_photo_1901_-_SMV_-_NR010.tif", "thumbnail": "https://upload.wikimedia.org/wikipedia/commons/thumb/0/09/Lisa_and_Albert_Ranft,_photo_1901_-_SMV_-_NR010.tif/500px-Lisa_and_Albert_Ranft,_photo_1901_-_SMV_-_NR010.tif.jpg", "desc": " Lisa och Albert Ranft, sk\u00e5despelare. Foto taget i bostaden 1901. Skannat glasnegativ\n", "auto_desc": {"translatedText": "Lisa and Albert Ranft, actor. Photo taken in the residence 1901. Scanned glass negative", "input": " Lisa och Albert Ranft, sk\u00e5despelare. Foto taget i bostaden 1901. Skannat glasnegativ\n"}}