{"media_id": "77484584", "local_id": "NR044\n", "title": "File:Axel_Ringvall_in_Surcouf_at_\u00d6stermalmsteatern_1905_-_SMV_-_NR044.tif", "thumbnail": "https://upload.wikimedia.org/wikipedia/commons/thumb/a/ac/Axel_Ringvall_in_Surcouf_at_\u00d6stermalmsteatern_1905_-_SMV_-_NR044.tif/500px-Axel_Ringvall_in_Surcouf_at_\u00d6stermalmsteatern_1905_-_SMV_-_NR044.tif.jpg", "desc": " Axel Ringvall som Gargousse i operetten Surcouf, \u00d6stermalmsteatern 1905. Skannat glasnegativ\n", "auto_desc": {"translatedText": "Axel Ringvall as Gargousse in the operetta Surcouf, \u00d6stermalmsteatern 1905. Scanned glass negative", "input": " Axel Ringvall som Gargousse i operetten Surcouf, \u00d6stermalmsteatern 1905. Skannat glasnegativ\n"}}