{"media_id": "77488937", "local_id": "NS141\n", "title": "File:Cornelia_Sundqvist,_actor_-_SMV_-_NS141.tif", "thumbnail": "https://upload.wikimedia.org/wikipedia/commons/thumb/5/5b/Cornelia_Sundqvist,_actor_-_SMV_-_NS141.tif/500px-Cornelia_Sundqvist,_actor_-_SMV_-_NS141.tif.jpg", "desc": " Cornelia Sundqvist, sk\u00e5despelare, i ok\u00e4nd f\u00f6rest\u00e4llning ca 1904. Skannat glasnegativ\n", "auto_desc": {"translatedText": "Cornelia Sundqvist, actor, in unknown performance about 1904. Scanned glass negative", "input": " Cornelia Sundqvist, sk\u00e5despelare, i ok\u00e4nd f\u00f6rest\u00e4llning ca 1904. Skannat glasnegativ\n"}}